Metadata-Version: 2.1
Name: JeriPy
Version: 0.1.2
Summary: JeriPy es una libreria que permite la traducción de espanol a Jerigonzo y de jerigonzo a espanol.
Home-page: https://github.com/Felipe1401/JeriPy.git
Author: Felipe Gomez
Author-email: felipenicolasgomezmolina@gmail.com
License: MIT
Classifier: Programming Language :: Python :: 3
Classifier: License :: OSI Approved :: MIT License
Classifier: Operating System :: OS Independent
Requires-Python: >=3.6
License-File: LICENSE
